LICENSE
MANIFEST.in
README.rst
requirements.txt
setup.cfg
setup.py
docs/README_PYPI.md
qrobot/__init__.py
qrobot/models/__init__.py
qrobot/models/angularmodel.py
qrobot/models/burstamodel.py
qrobot/models/linearmodel.py
qrobot/models/model.py
qrobot/tests/__init__.py
qrobot/tests/test_angularmodel.py
qrobot/tests/test_burstamodel.py
qrobot/tests/test_linearmodel.py
quantum_robot.egg-info/PKG-INFO
quantum_robot.egg-info/SOURCES.txt
quantum_robot.egg-info/dependency_links.txt
quantum_robot.egg-info/requires.txt
quantum_robot.egg-info/top_level.txt