Metadata-Version: 2.1
Name: quantum-robot
Version: 0.1
Summary: A set of python modules for quantum-like perception modelling
Home-page: http://quantum-robot.org
Author: Davide Lanza
Author-email: davidel96@hotmail.it
Maintainer: Davide Lanza
Maintainer-email: davidel96@hotmail.it
License: GNU GPL
Download-URL: https://pypi.org/project/quantum-robot/#files
Project-URL: Bug Tracker, https://github.com/Davidelanz/quantum-robot/issues
Project-URL: Documentation, http://quantum-robot.org/docs
Project-URL: Source Code, https://github.com/Davidelanz/quantum-robot
Platform: UNKNOWN
Classifier: Programming Language :: Python :: 3
Classifier: License :: OSI Approved :: GNU General Public License (GPL)
Classifier: Operating System :: OS Independent
Classifier: Development Status :: 3 - Alpha
Classifier: Intended Audience :: Science/Research
Classifier: Natural Language :: English
Classifier: Programming Language :: Python :: 3
Classifier: Topic :: Scientific/Engineering :: Artificial Intelligence
Requires-Python: >=3.6
